reggy/__init__.py
reggy/families.py
reggy/main.py
reggy/model.py
reggy/regularizers.py
reggy/utils.py
reggy-0.2.0.dist-info/LICENSE
reggy-0.2.0.dist-info/WHEEL
reggy-0.2.0.dist-info/METADATA
reggy-0.2.0.dist-info/RECORD
