Metadata-Version: 2.1
Name: reggy
Version: 0.2.0
Summary: Python package for regularized regressions.
Home-page: https://github.com/kpj/reggy
License: MIT
Author: kpj
Author-email: kim.philipp.jablonski@gmail.com
Requires-Python: >=3.9.0,<3.10.0
Classifier: License :: OSI Approved :: MIT License
Classifier: Programming Language :: Python :: 3
Classifier: Programming Language :: Python :: 3.9
Requires-Dist: pandas (>=1.3.5,<2.0.0)
Requires-Dist: tensorflow (>=2.7.0,<3.0.0)
Requires-Dist: tensorflow-probability (>=0.15.0,<0.16.0)
Project-URL: Repository, https://github.com/kpj/reggy
